aws/__init__.py
aws/common.py
aws/ec2.py
aws_parallelcluster_node-3.14.1.dist-info/licenses/LICENSE.txt
aws_parallelcluster_node-3.14.1.dist-info/licenses/NOTICE.txt
common/__init__.py
common/ec2_utils.py
common/time_utils.py
common/utils.py
common/schedulers/__init__.py
common/schedulers/slurm_commands.py
common/schedulers/slurm_reservation_commands.py
slurm_plugin/__init__.py
slurm_plugin/capacity_block_manager.py
slurm_plugin/cluster_event_publisher.py
slurm_plugin/clustermgtd.py
slurm_plugin/common.py
slurm_plugin/computemgtd.py
slurm_plugin/console_logger.py
slurm_plugin/fleet_manager.py
slurm_plugin/fleet_status_manager.py
slurm_plugin/instance_manager.py
slurm_plugin/resume.py
slurm_plugin/slurm_resources.py
slurm_plugin/suspend.py
slurm_plugin/task_executor.py
slurm_plugin/logging/parallelcluster_clustermgtd_logging.conf
slurm_plugin/logging/parallelcluster_computemgtd_logging.conf
slurm_plugin/logging/parallelcluster_fleet_status_manager_logging.conf
slurm_plugin/logging/parallelcluster_resume_logging.conf
slurm_plugin/logging/parallelcluster_suspend_logging.conf
aws_parallelcluster_node-3.14.1.dist-info/METADATA
aws_parallelcluster_node-3.14.1.dist-info/WHEEL
aws_parallelcluster_node-3.14.1.dist-info/entry_points.txt
aws_parallelcluster_node-3.14.1.dist-info/top_level.txt
aws_parallelcluster_node-3.14.1.dist-info/RECORD
