Metadata-Version: 2.4
Name: aws-parallelcluster-node
Version: 3.14.1
Summary: aws-parallelcluster-node provides the scripts for an AWS ParallelCluster node.
Home-page: https://github.com/aws/aws-parallelcluster-node
Author: Amazon Web Services
License: Apache License 2.0
Classifier: Development Status :: 5 - Production/Stable
Classifier: Environment :: Console
Classifier: Programming Language :: Python
Classifier: Topic :: Scientific/Engineering
Classifier: License :: OSI Approved :: Apache Software License
Requires-Python: >=3.9
License-File: LICENSE.txt
License-File: NOTICE.txt
Requires-Dist: boto3>=1.7.55
Requires-Dist: retrying>=1.3.3
Dynamic: author
Dynamic: classifier
Dynamic: description
Dynamic: home-page
Dynamic: license
Dynamic: license-file
Dynamic: requires-dist
Dynamic: requires-python
Dynamic: summary
